dacsspace/__init__.py
dacsspace/client.py
dacsspace/command_line.py
dacsspace/dacsspace.py
dacsspace/reporter.py
dacsspace/validator.py
tests/__init__.py
tests/test_client.py
tests/test_commandline.py
tests/test_dacsspace.py
tests/test_reporter.py
tests/test_validator.py
dacsspace-0.1.1.dist-info/LICENSE
dacsspace-0.1.1.dist-info/METADATA
dacsspace-0.1.1.dist-info/WHEEL
dacsspace-0.1.1.dist-info/entry_points.txt
dacsspace-0.1.1.dist-info/top_level.txt
dacsspace-0.1.1.dist-info/RECORD
