Metadata-Version: 2.1
Name: dacsspace
Version: 0.1.1
Summary: Validate data in an ArchivesSpace instance against DACS requirements.
Home-page: https://github.com/RockefellerArchiveCenter/DACSspace
Author: Rockefeller Archive Center
Author-email: archive@rockarch.org
License: MIT
Platform: UNKNOWN
Classifier: Programming Language :: Python :: 3
Classifier: Intended Audience :: Other Audience
Classifier: License :: OSI Approved :: MIT License
Requires-Python: >=3.7
License-File: LICENSE
Requires-Dist: jsonschema
Requires-Dist: requests
